LICENSE
MANIFEST.in
README.md
setup.py
RapidXml.egg-info/PKG-INFO
RapidXml.egg-info/SOURCES.txt
RapidXml.egg-info/dependency_links.txt
RapidXml.egg-info/top_level.txt
rapidxml/__init__.py
rapidxml/rapidxml.py
rapidxml/c_ext/inc/common.h
rapidxml/c_ext/inc/rapidxml-1.13/rapidxml.hpp
rapidxml/c_ext/inc/rapidxml-1.13/rapidxml_iterators.hpp
rapidxml/c_ext/inc/rapidxml-1.13/rapidxml_print.hpp
rapidxml/c_ext/inc/rapidxml-1.13/rapidxml_utils.hpp
rapidxml/c_ext/src/attribute_object.cpp
rapidxml/c_ext/src/attributeiterator_object.cpp
rapidxml/c_ext/src/base_object.cpp
rapidxml/c_ext/src/common.cpp
rapidxml/c_ext/src/document_object.cpp
rapidxml/c_ext/src/node_object.cpp
rapidxml/c_ext/src/nodeiterator_object.cpp
rapidxml/c_ext/src/rapidxml_module.cpp